daily_hn.py
daily_hn-0.1.5.dist-info/entry_points.txt
daily_hn-0.1.5.dist-info/LICENSE
daily_hn-0.1.5.dist-info/WHEEL
daily_hn-0.1.5.dist-info/METADATA
daily_hn-0.1.5.dist-info/RECORD
