Metadata-Version: 2.1
Name: daily-hn
Version: 0.1.5
Summary: A command line tool for displaying and opening links to the current best stories from news.ycombinator.com (Hacker News)
Home-page: https://github.com/Rolv-Apneseth/daily_hn/
License: MIT
Author: Rolv-Apneseth
Author-email: rolv.apneseth@gmail.com
Requires-Python: >=3.9,<4.0.0
Classifier: License :: OSI Approved :: MIT License
Classifier: Programming Language :: Python :: 3
Classifier: Programming Language :: Python :: 3.9
Classifier: Programming Language :: Python :: 3.10
Classifier: Programming Language :: Python :: 3.11
Requires-Dist: beautifulsoup4 (>=4.10.0,<5.0.0)
Requires-Dist: requests (>=2.27.1,<3.0.0)
